{
  "type": "collection",
  "entry": [
    {
      "fullUrl": "urn:uuid:aa45a301-29d4-4ae6-a379-8efda70a0df4",
      "resource": {
        "id": "aa45a301-29d4-4ae6-a379-8efda70a0df4",
        "meta": {
          "profile": [
            "http://standardhealthrecord.org/fhir/StructureDefinition/shr-demographics-PersonOfRecord"
          ]
        },
        "text": {
          "status": "generated",
          "div": "<div>Generated by <a href=\"https://github.com/synthetichealth/synthea\">Synthea</a>. Version identifier: 4d02400401b9fab839e47bf5b2f1f6a8c683ab55</div>"
        },
        "extension": [
          {
            "url": "http://hl7.org/fhir/us/core/StructureDefinition/us-core-race",
            "valueCodeableConcept": {
              "coding": [
                {
                  "system": "http://hl7.org/fhir/v3/Race",
                  "code": "2106-3",
                  "display": "White"
                }
              ],
              "text": "race"
            }
          },
          {
            "url": "http://hl7.org/fhir/us/core/StructureDefinition/us-core-ethnicity",
            "valueCodeableConcept": {
              "coding": [
                {
                  "system": "http://hl7.org/fhir/v3/Ethnicity",
                  "code": "2186-5",
                  "display": "Nonhispanic"
                }
              ],
              "text": "ethnicity"
            }
          },
          {
            "url": "http://hl7.org/fhir/StructureDefinition/birthPlace",
            "valueAddress": {
              "city": "Gloucester",
              "state": "MA",
              "country": "US"
            }
          },
          {
            "url": "http://hl7.org/fhir/StructureDefinition/patient-mothersMaidenName",
            "valueString": "Paolo804 Koss561"
          },
          {
            "url": "http://hl7.org/fhir/us/core/StructureDefinition/us-core-birthsex",
            "valueCode": "M"
          },
          {
            "url": "http://hl7.org/fhir/StructureDefinition/patient-interpreterRequired",
            "valueBoolean": false
          },
          {
            "url": "http://standardhealthrecord.org/fhir/StructureDefinition/shr-actor-FictionalPerson-extension",
            "valueBoolean": true
          },
          {
            "url": "http://standardhealthrecord.org/fhir/StructureDefinition/shr-demographics-FathersName-extension",
            "valueHumanName": {
              "text": "Lincoln771 Abernathy959"
            }
          },
          {
            "url": "http://standardhealthrecord.org/fhir/StructureDefinition/shr-demographics-SocialSecurityNumber-extension",
            "valueString": "999-96-3108"
          }
        ],
        "identifier": [
          {
            "system": "https://github.com/synthetichealth/synthea",
            "value": "b472a972-3176-4619-a2d9-7b2610f1f917"
          },
          {
            "type": {
              "coding": [
                {
                  "system": "http://hl7.org/fhir/identifier-type",
                  "code": "SB"
                }
              ]
            },
            "system": "http://hl7.org/fhir/sid/us-ssn",
            "value": "999963108"
          },
          {
            "type": {
              "coding": [
                {
                  "system": "http://hl7.org/fhir/v2/0203",
                  "code": "DL"
                }
              ]
            },
            "system": "urn:oid:2.16.840.1.113883.4.3.25",
            "value": "S99987982"
          }
        ],
        "name": [
          {
            "use": "official",
            "family": "Abernathy959",
            "given": [
              "Roberta713"
            ],
            "prefix": [
              "Mr."
            ]
          }
        ],
        "telecom": [
          {
            "system": "phone",
            "value": "845-427-9019",
            "use": "home"
          }
        ],
        "gender": "male",
        "birthDate": "1984-04-16",
        "address": [
          {
            "extension": [
              {
                "extension": [
                  {
                    "url": "latitude",
                    "valueDecimal": 42.559067182493465
                  },
                  {
                    "url": "longitude",
                    "valueDecimal": -70.87348233347466
                  }
                ],
                "url": "http://hl7.org/fhir/StructureDefinition/geolocation"
              }
            ],
            "line": [
              "71799 Eduardo Shore"
            ],
            "city": "Beverly",
            "state": "MA",
            "postalCode": "01915",
            "country": "US"
          }
        ],
        "maritalStatus": {
          "coding": [
            {
              "system": "http://hl7.org/fhir/v3/MaritalStatus",
              "code": "S"
            }
          ],
          "text": "S"
        },
        "multipleBirthBoolean": false,
        "communication": [
          {
            "language": {
              "coding": [
                {
                  "system": "http://hl7.org/fhir/ValueSet/languages",
                  "code": "en-US",
                  "display": "English (United States)"
                }
              ]
            }
          }
        ],
        "resourceType": "Patient"
      }
    },
    {
      "fullUrl": "urn:uuid:24180124-c1f3-45ef-9f02-7a0f74f9ff82",
      "resource": {
        "id": "24180124-c1f3-45ef-9f02-7a0f74f9ff82",
        "meta": {
          "profile": [
            "http://standardhealthrecord.org/fhir/StructureDefinition/shr-actor-Organization"
          ]
        },
        "type": [
          {
            "coding": [
              {
                "system": "http://hl7.org/fhir/ValueSet/organization-type",
                "code": "prov",
                "display": "Healthcare Provider"
              }
            ],
            "text": "Healthcare Provider"
          }
        ],
        "name": "Synthetic Provider",
        "resourceType": "Organization"
      }
    },
    {
      "fullUrl": "urn:uuid:8ab59244-61fc-490a-97a8-03f8468f1e21",
      "resource": {
        "id": "8ab59244-61fc-490a-97a8-03f8468f1e21",
        "meta": {
          "profile": [
            "http://standardhealthrecord.org/fhir/StructureDefinition/shr-encounter-Encounter"
          ]
        },
        "status": "finished",
        "class": {
          "code": "outpatient"
        },
        "type": [
          {
            "coding": [
              {
                "system": "http://snomed.info/sct",
                "code": "185349003"
              }
            ],
            "text": "Outpatient Encounter"
          }
        ],
        "subject": {
          "reference": "urn:uuid:aa45a301-29d4-4ae6-a379-8efda70a0df4"
        },
        "period": {
          "start": "2011-06-27T01:20:02-04:00",
          "end": "2011-06-27T02:20:02-04:00"
        },
        "serviceProvider": {
          "reference": "urn:uuid:24180124-c1f3-45ef-9f02-7a0f74f9ff82"
        },
        "resourceType": "Encounter"
      }
    },
    {
      "fullUrl": "urn:uuid:c3035872-5ac0-419a-866d-5d7639707e17",
      "resource": {
        "id": "c3035872-5ac0-419a-866d-5d7639707e17",
        "meta": {
          "profile": [
            "http://standardhealthrecord.org/fhir/StructureDefinition/shr-problem-Problem"
          ]
        },
        "clinicalStatus": "active",
        "verificationStatus": "confirmed",
        "code": {
          "coding": [
            {
              "system": "http://snomed.info/sct",
              "code": "446096008",
              "display": "Perennial allergic rhinitis"
            }
          ],
          "text": "Perennial allergic rhinitis"
        },
        "subject": {
          "reference": "urn:uuid:aa45a301-29d4-4ae6-a379-8efda70a0df4"
        },
        "context": {
          "reference": "urn:uuid:8ab59244-61fc-490a-97a8-03f8468f1e21"
        },
        "onsetDateTime": "1986-06-14T11:35:40-04:00",
        "assertedDate": "1986-06-14",
        "resourceType": "Condition"
      }
    },
    {
      "resource": {
        "meta": {
          "profile": [
            "http://standardhealthrecord.org/fhir/StructureDefinition/shr-allergy-AllergyIntolerance"
          ]
        },
        "modifierExtension": [
          {
            "extension": [
              {
                "url": "http://standardhealthrecord.org/fhir/StructureDefinition/primitive-boolean-extension",
                "valueBoolean": false
              }
            ],
            "url": "http://standardhealthrecord.org/fhir/StructureDefinition/shr-base-NonOccurrenceModifier-extension"
          }
        ],
        "clinicalStatus": "active",
        "verificationStatus": "confirmed",
        "type": "allergy",
        "category": [
          "food"
        ],
        "criticality": "high",
        "code": {
          "coding": [
            {
              "system": "http://snomed.info/sct",
              "code": "419263009",
              "display": "Allergy to tree pollen"
            }
          ]
        },
        "patient": {
          "reference": "urn:uuid:aa45a301-29d4-4ae6-a379-8efda70a0df4"
        },
        "assertedDate": "1986-06-18T09:15:28-04:00",
        "resourceType": "AllergyIntolerance"
      }
    },
    {
      "resource": {
        "meta": {
          "profile": [
            "http://standardhealthrecord.org/fhir/StructureDefinition/shr-allergy-AllergyIntolerance"
          ]
        },
        "modifierExtension": [
          {
            "extension": [
              {
                "url": "http://standardhealthrecord.org/fhir/StructureDefinition/primitive-boolean-extension",
                "valueBoolean": false
              }
            ],
            "url": "http://standardhealthrecord.org/fhir/StructureDefinition/shr-base-NonOccurrenceModifier-extension"
          }
        ],
        "clinicalStatus": "active",
        "verificationStatus": "confirmed",
        "type": "allergy",
        "category": [
          "food"
        ],
        "criticality": "high",
        "code": {
          "coding": [
            {
              "system": "http://snomed.info/sct",
              "code": "418689008",
              "display": "Allergy to grass pollen"
            }
          ]
        },
        "patient": {
          "reference": "urn:uuid:aa45a301-29d4-4ae6-a379-8efda70a0df4"
        },
        "assertedDate": "1986-06-18T09:15:28-04:00",
        "resourceType": "AllergyIntolerance"
      }
    },
    {
      "resource": {
        "meta": {
          "profile": [
            "http://standardhealthrecord.org/fhir/StructureDefinition/shr-allergy-AllergyIntolerance"
          ]
        },
        "modifierExtension": [
          {
            "extension": [
              {
                "url": "http://standardhealthrecord.org/fhir/StructureDefinition/primitive-boolean-extension",
                "valueBoolean": false
              }
            ],
            "url": "http://standardhealthrecord.org/fhir/StructureDefinition/shr-base-NonOccurrenceModifier-extension"
          }
        ],
        "clinicalStatus": "active",
        "verificationStatus": "confirmed",
        "type": "allergy",
        "category": [
          "food"
        ],
        "criticality": "high",
        "code": {
          "coding": [
            {
              "system": "http://snomed.info/sct",
              "code": "232347008",
              "display": "Dander (animal) allergy"
            }
          ]
        },
        "patient": {
          "reference": "urn:uuid:aa45a301-29d4-4ae6-a379-8efda70a0df4"
        },
        "assertedDate": "1986-06-18T09:15:28-04:00",
        "resourceType": "AllergyIntolerance"
      }
    },
    {
      "resource": {
        "meta": {
          "profile": [
            "http://standardhealthrecord.org/fhir/StructureDefinition/shr-allergy-AllergyIntolerance"
          ]
        },
        "modifierExtension": [
          {
            "extension": [
              {
                "url": "http://standardhealthrecord.org/fhir/StructureDefinition/primitive-boolean-extension",
                "valueBoolean": false
              }
            ],
            "url": "http://standardhealthrecord.org/fhir/StructureDefinition/shr-base-NonOccurrenceModifier-extension"
          }
        ],
        "clinicalStatus": "active",
        "verificationStatus": "confirmed",
        "type": "allergy",
        "category": [
          "food"
        ],
        "criticality": "low",
        "code": {
          "coding": [
            {
              "system": "http://snomed.info/sct",
              "code": "232350006",
              "display": "House dust mite allergy"
            }
          ]
        },
        "patient": {
          "reference": "urn:uuid:aa45a301-29d4-4ae6-a379-8efda70a0df4"
        },
        "assertedDate": "1986-06-18T09:15:28-04:00",
        "resourceType": "AllergyIntolerance"
      }
    },
    {
      "resource": {
        "meta": {
          "profile": [
            "http://standardhealthrecord.org/fhir/StructureDefinition/shr-allergy-AllergyIntolerance"
          ]
        },
        "modifierExtension": [
          {
            "extension": [
              {
                "url": "http://standardhealthrecord.org/fhir/StructureDefinition/primitive-boolean-extension",
                "valueBoolean": false
              }
            ],
            "url": "http://standardhealthrecord.org/fhir/StructureDefinition/shr-base-NonOccurrenceModifier-extension"
          }
        ],
        "clinicalStatus": "active",
        "verificationStatus": "confirmed",
        "type": "allergy",
        "category": [
          "food"
        ],
        "criticality": "high",
        "code": {
          "coding": [
            {
              "system": "http://snomed.info/sct",
              "code": "419474003",
              "display": "Allergy to mould"
            }
          ]
        },
        "patient": {
          "reference": "urn:uuid:aa45a301-29d4-4ae6-a379-8efda70a0df4"
        },
        "assertedDate": "1986-06-18T09:15:28-04:00",
        "resourceType": "AllergyIntolerance"
      }
    },
    {
      "resource": {
        "meta": {
          "profile": [
            "http://standardhealthrecord.org/fhir/StructureDefinition/shr-allergy-AllergyIntolerance"
          ]
        },
        "modifierExtension": [
          {
            "extension": [
              {
                "url": "http://standardhealthrecord.org/fhir/StructureDefinition/primitive-boolean-extension",
                "valueBoolean": false
              }
            ],
            "url": "http://standardhealthrecord.org/fhir/StructureDefinition/shr-base-NonOccurrenceModifier-extension"
          }
        ],
        "clinicalStatus": "active",
        "verificationStatus": "confirmed",
        "type": "allergy",
        "category": [
          "food"
        ],
        "criticality": "low",
        "code": {
          "coding": [
            {
              "system": "http://snomed.info/sct",
              "code": "424213003",
              "display": "Allergy to bee venom"
            }
          ]
        },
        "patient": {
          "reference": "urn:uuid:aa45a301-29d4-4ae6-a379-8efda70a0df4"
        },
        "assertedDate": "1986-06-18T09:15:28-04:00",
        "resourceType": "AllergyIntolerance"
      }
    },
    {
      "fullUrl": "urn:uuid:ac3173bf-e592-4f47-b950-6465401ad9ff",
      "resource": {
        "id": "ac3173bf-e592-4f47-b950-6465401ad9ff",
        "meta": {
          "profile": [
            "http://standardhealthrecord.org/fhir/StructureDefinition/shr-problem-Problem"
          ]
        },
        "clinicalStatus": "active",
        "verificationStatus": "confirmed",
        "code": {
          "coding": [
            {
              "system": "http://snomed.info/sct",
              "code": "24079001",
              "display": "Atopic dermatitis"
            }
          ],
          "text": "Atopic dermatitis"
        },
        "subject": {
          "reference": "urn:uuid:aa45a301-29d4-4ae6-a379-8efda70a0df4"
        },
        "context": {
          "reference": "urn:uuid:8ab59244-61fc-490a-97a8-03f8468f1e21"
        },
        "onsetDateTime": "1988-09-05T00:52:54-04:00",
        "assertedDate": "1988-09-05",
        "resourceType": "Condition"
      }
    },
    {
      "fullUrl": "urn:uuid:2a4df234-96c1-47bc-9569-deeb4a951bc1",
      "resource": {
        "id": "2a4df234-96c1-47bc-9569-deeb4a951bc1",
        "meta": {
          "profile": [
            "http://standardhealthrecord.org/fhir/StructureDefinition/shr-observation-Observation",
            "http://standardhealthrecord.org/fhir/StructureDefinition/shr-vital-VitalSign",
            "http://standardhealthrecord.org/fhir/StructureDefinition/shr-vital-BodyHeight"
          ]
        },
        "status": "final",
        "category": [
          {
            "coding": [
              {
                "system": "http://hl7.org/fhir/observation-category",
                "code": "vital-signs"
              }
            ]
          }
        ],
        "code": {
          "coding": [
            {
              "system": "http://loinc.org",
              "code": "8302-2",
              "display": "Body Height"
            }
          ],
          "text": "Body Height"
        },
        "subject": {
          "reference": "urn:uuid:aa45a301-29d4-4ae6-a379-8efda70a0df4"
        },
        "context": {
          "reference": "urn:uuid:8ab59244-61fc-490a-97a8-03f8468f1e21"
        },
        "effectiveDateTime": "2011-06-27T01:20:02-04:00",
        "issued": "2011-06-27T01:20:02-04:00",
        "valueQuantity": {
          "value": 190.1848657986878,
          "unit": "cm",
          "system": "http://unitsofmeasure.org/",
          "code": "cm"
        },
        "resourceType": "Observation"
      }
    },
    {
      "fullUrl": "urn:uuid:343386db-640d-495f-a283-15b81285945e",
      "resource": {
        "id": "343386db-640d-495f-a283-15b81285945e",
        "meta": {
          "profile": [
            "http://standardhealthrecord.org/fhir/StructureDefinition/shr-observation-Observation",
            "http://standardhealthrecord.org/fhir/StructureDefinition/shr-vital-VitalSign",
            "http://standardhealthrecord.org/fhir/StructureDefinition/shr-vital-BodyWeight"
          ]
        },
        "status": "final",
        "category": [
          {
            "coding": [
              {
                "system": "http://hl7.org/fhir/observation-category",
                "code": "vital-signs"
              }
            ]
          }
        ],
        "code": {
          "coding": [
            {
              "system": "http://loinc.org",
              "code": "29463-7",
              "display": "Body Weight"
            }
          ],
          "text": "Body Weight"
        },
        "subject": {
          "reference": "urn:uuid:aa45a301-29d4-4ae6-a379-8efda70a0df4"
        },
        "context": {
          "reference": "urn:uuid:8ab59244-61fc-490a-97a8-03f8468f1e21"
        },
        "effectiveDateTime": "2011-06-27T01:20:02-04:00",
        "issued": "2011-06-27T01:20:02-04:00",
        "valueQuantity": {
          "value": 88.26671572093456,
          "unit": "kg",
          "system": "http://unitsofmeasure.org/",
          "code": "kg"
        },
        "resourceType": "Observation"
      }
    },
    {
      "fullUrl": "urn:uuid:003b135e-729c-480c-82ff-1218b28eb36d",
      "resource": {
        "id": "003b135e-729c-480c-82ff-1218b28eb36d",
        "meta": {
          "profile": [
            "http://standardhealthrecord.org/fhir/StructureDefinition/shr-observation-Observation",
            "http://standardhealthrecord.org/fhir/StructureDefinition/shr-vital-VitalSign",
            "http://standardhealthrecord.org/fhir/StructureDefinition/shr-vital-BodyMassIndex"
          ]
        },
        "status": "final",
        "category": [
          {
            "coding": [
              {
                "system": "http://hl7.org/fhir/observation-category",
                "code": "vital-signs"
              }
            ]
          }
        ],
        "code": {
          "coding": [
            {
              "system": "http://loinc.org",
              "code": "39156-5",
              "display": "Body Mass Index"
            }
          ],
          "text": "Body Mass Index"
        },
        "subject": {
          "reference": "urn:uuid:aa45a301-29d4-4ae6-a379-8efda70a0df4"
        },
        "context": {
          "reference": "urn:uuid:8ab59244-61fc-490a-97a8-03f8468f1e21"
        },
        "effectiveDateTime": "2011-06-27T01:20:02-04:00",
        "issued": "2011-06-27T01:20:02-04:00",
        "valueQuantity": {
          "value": 24.40310331120404,
          "unit": "kg/m2",
          "system": "http://unitsofmeasure.org/",
          "code": "kg/m2"
        },
        "resourceType": "Observation"
      }
    },
    {
      "fullUrl": "urn:uuid:88249b89-9a58-424d-90e3-a32245efd02f",
      "resource": {
        "id": "88249b89-9a58-424d-90e3-a32245efd02f",
        "meta": {
          "profile": [
            "http://standardhealthrecord.org/fhir/StructureDefinition/shr-observation-Observation",
            "http://standardhealthrecord.org/fhir/StructureDefinition/shr-vital-BloodPressure"
          ]
        },
        "status": "final",
        "category": [
          {
            "coding": [
              {
                "system": "http://hl7.org/fhir/observation-category",
                "code": "vital-signs"
              }
            ]
          }
        ],
        "code": {
          "coding": [
            {
              "system": "http://loinc.org",
              "code": "55284-4",
              "display": "Blood Pressure"
            }
          ]
        },
        "subject": {
          "reference": "urn:uuid:aa45a301-29d4-4ae6-a379-8efda70a0df4"
        },
        "context": {
          "reference": "urn:uuid:8ab59244-61fc-490a-97a8-03f8468f1e21"
        },
        "effectiveDateTime": "2011-06-27T01:20:02-04:00",
        "issued": "2011-06-27T01:20:02-04:00",
        "component": [
          {
            "code": {
              "coding": [
                {
                  "system": "http://loinc.org",
                  "code": "8480-6",
                  "display": "Systolic Blood Pressure"
                }
              ],
              "text": "Systolic Blood Pressure"
            },
            "valueQuantity": {
              "value": 122,
              "unit": "mmHg",
              "system": "http://unitsofmeasure.org/",
              "code": "mmHg"
            }
          },
          {
            "code": {
              "coding": [
                {
                  "system": "http://loinc.org",
                  "code": "8462-4",
                  "display": "Diastolic Blood Pressure"
                }
              ],
              "text": "Diastolic Blood Pressure"
            },
            "valueQuantity": {
              "value": 86,
              "unit": "mmHg",
              "system": "http://unitsofmeasure.org/",
              "code": "mmHg"
            }
          }
        ],
        "resourceType": "Observation"
      }
    },
    {
      "resource": {
        "meta": {
          "profile": [
            "http://standardhealthrecord.org/fhir/StructureDefinition/shr-procedure-Procedure"
          ]
        },
        "extension": [
          {
            "url": "http://standardhealthrecord.org/fhir/StructureDefinition/shr-core-CodeableConcept-extension",
            "valueCodeableConcept": {
              "coding": [
                {
                  "system": "http://snomed.info/sct",
                  "code": "428191000124101",
                  "display": "Documentation of current medications"
                }
              ],
              "text": "Documentation of current medications"
            }
          }
        ],
        "status": "completed",
        "code": {
          "coding": [
            {
              "system": "http://snomed.info/sct",
              "code": "428191000124101",
              "display": "Documentation of current medications"
            }
          ],
          "text": "Documentation of current medications"
        },
        "subject": {
          "reference": "urn:uuid:aa45a301-29d4-4ae6-a379-8efda70a0df4"
        },
        "context": {
          "reference": "urn:uuid:8ab59244-61fc-490a-97a8-03f8468f1e21"
        },
        "performedDateTime": "2011-06-27T01:20:02-04:00",
        "resourceType": "Procedure"
      }
    },
    {
      "resource": {
        "meta": {
          "profile": [
            "http://standardhealthrecord.org/fhir/StructureDefinition/shr-immunization-Immunization"
          ]
        },
        "status": "completed",
        "notGiven": false,
        "vaccineCode": {
          "coding": [
            {
              "system": "http://hl7.org/fhir/sid/cvx",
              "code": "140",
              "display": "Influenza, seasonal, injectable, preservative free"
            }
          ],
          "text": "Influenza, seasonal, injectable, preservative free"
        },
        "patient": {
          "reference": "urn:uuid:aa45a301-29d4-4ae6-a379-8efda70a0df4"
        },
        "encounter": {
          "reference": "urn:uuid:8ab59244-61fc-490a-97a8-03f8468f1e21"
        },
        "date": "2011-06-27T01:20:02-04:00",
        "primarySource": true,
        "resourceType": "Immunization"
      }
    },
    {
      "resource": {
        "status": "active",
        "category": [
          {
            "coding": [
              {
                "system": "http://snomed.info/sct",
                "code": "326051000000105",
                "display": "Self care"
              }
            ]
          }
        ],
        "subject": {
          "reference": "urn:uuid:aa45a301-29d4-4ae6-a379-8efda70a0df4"
        },
        "context": {
          "reference": "urn:uuid:8ab59244-61fc-490a-97a8-03f8468f1e21"
        },
        "period": {
          "start": "1986-06-18"
        },
        "activity": [
          {
            "detail": {
              "code": {
                "coding": [
                  {
                    "system": "http://snomed.info/sct",
                    "code": "58332002",
                    "display": "Allergy education"
                  }
                ]
              },
              "status": "in-progress"
            }
          }
        ],
        "resourceType": "CarePlan"
      }
    },
    {
      "resource": {
        "status": "active",
        "category": [
          {
            "coding": [
              {
                "system": "http://snomed.info/sct",
                "code": "711282006",
                "display": "Skin condition care"
              }
            ]
          }
        ],
        "subject": {
          "reference": "urn:uuid:aa45a301-29d4-4ae6-a379-8efda70a0df4"
        },
        "context": {
          "reference": "urn:uuid:8ab59244-61fc-490a-97a8-03f8468f1e21"
        },
        "period": {
          "start": "1988-09-05"
        },
        "addresses": [
          {
            "reference": "urn:uuid:ac3173bf-e592-4f47-b950-6465401ad9ff"
          }
        ],
        "activity": [
          {
            "detail": {
              "code": {
                "coding": [
                  {
                    "system": "http://snomed.info/sct",
                    "code": "225130001",
                    "display": "Application of moisturizer to skin"
                  }
                ]
              },
              "status": "in-progress"
            }
          }
        ],
        "resourceType": "CarePlan"
      }
    },
    {
      "resource": {
        "meta": {
          "profile": [
            "http://standardhealthrecord.org/fhir/StructureDefinition/shr-medication-Medication"
          ]
        },
        "code": {
          "coding": [
            {
              "system": "http://www.nlm.nih.gov/research/umls/rxnorm",
              "code": "197378",
              "display": "Astemizole 10 MG Oral Tablet"
            }
          ],
          "text": "Astemizole 10 MG Oral Tablet"
        },
        "resourceType": "Medication"
      }
    },
    {
      "resource": {
        "meta": {
          "profile": [
            "http://standardhealthrecord.org/fhir/StructureDefinition/shr-medication-MedicationPrescription"
          ]
        },
        "extension": [
          {
            "url": "http://standardhealthrecord.org/fhir/StructureDefinition/shr-base-ActionCode-extension",
            "valueCodeableConcept": {
              "coding": [
                {
                  "system": "http://snomed.info/sct",
                  "code": "33633005",
                  "display": "Prescription of drug (procedure)"
                }
              ],
              "text": "Prescription of drug (procedure)"
            }
          }
        ],
        "status": "active",
        "medicationReference": {
          "reference": ""
        },
        "subject": {
          "reference": "urn:uuid:aa45a301-29d4-4ae6-a379-8efda70a0df4"
        },
        "context": {
          "reference": "urn:uuid:8ab59244-61fc-490a-97a8-03f8468f1e21"
        },
        "authoredOn": "1986-06-14",
        "dosageInstruction": [
          {
            "sequence": 1,
            "asNeededBoolean": true
          }
        ],
        "resourceType": "MedicationRequest"
      }
    },
    {
      "resource": {
        "meta": {
          "profile": [
            "http://standardhealthrecord.org/fhir/StructureDefinition/shr-medication-Medication"
          ]
        },
        "code": {
          "coding": [
            {
              "system": "http://www.nlm.nih.gov/research/umls/rxnorm",
              "code": "834060",
              "display": "Penicillin V Potassium 250 MG"
            }
          ],
          "text": "Penicillin V Potassium 250 MG"
        },
        "resourceType": "Medication"
      }
    },
    {
      "resource": {
        "meta": {
          "profile": [
            "http://standardhealthrecord.org/fhir/StructureDefinition/shr-medication-MedicationPrescription"
          ]
        },
        "extension": [
          {
            "url": "http://standardhealthrecord.org/fhir/StructureDefinition/shr-base-ActionCode-extension",
            "valueCodeableConcept": {
              "coding": [
                {
                  "system": "http://snomed.info/sct",
                  "code": "33633005",
                  "display": "Prescription of drug (procedure)"
                }
              ],
              "text": "Prescription of drug (procedure)"
            }
          }
        ],
        "status": "active",
        "medicationReference": {
          "reference": ""
        },
        "subject": {
          "reference": "urn:uuid:aa45a301-29d4-4ae6-a379-8efda70a0df4"
        },
        "context": {
          "reference": "urn:uuid:8ab59244-61fc-490a-97a8-03f8468f1e21"
        },
        "authoredOn": "1997-01-12",
        "dosageInstruction": [
          {

          }
        ],
        "resourceType": "MedicationRequest"
      }
    },
    {
      "resource": {
        "meta": {
          "profile": [
            "http://standardhealthrecord.org/fhir/StructureDefinition/shr-medication-Medication"
          ]
        },
        "code": {
          "coding": [
            {
              "system": "http://www.nlm.nih.gov/research/umls/rxnorm",
              "code": "834101",
              "display": "Penicillin V Potassium 500 MG"
            }
          ],
          "text": "Penicillin V Potassium 500 MG"
        },
        "resourceType": "Medication"
      }
    },
    {
      "resource": {
        "meta": {
          "profile": [
            "http://standardhealthrecord.org/fhir/StructureDefinition/shr-medication-MedicationPrescription"
          ]
        },
        "extension": [
          {
            "url": "http://standardhealthrecord.org/fhir/StructureDefinition/shr-base-ActionCode-extension",
            "valueCodeableConcept": {
              "coding": [
                {
                  "system": "http://snomed.info/sct",
                  "code": "33633005",
                  "display": "Prescription of drug (procedure)"
                }
              ],
              "text": "Prescription of drug (procedure)"
            }
          }
        ],
        "status": "active",
        "medicationReference": {
          "reference": ""
        },
        "subject": {
          "reference": "urn:uuid:aa45a301-29d4-4ae6-a379-8efda70a0df4"
        },
        "context": {
          "reference": "urn:uuid:8ab59244-61fc-490a-97a8-03f8468f1e21"
        },
        "authoredOn": "2004-04-11",
        "dosageInstruction": [
          {

          }
        ],
        "resourceType": "MedicationRequest"
      }
    },
    {
      "fullUrl": "urn:uuid:2646424d-6b8d-4dfe-8cd8-8fc333ab3759",
      "resource": {
        "id": "2646424d-6b8d-4dfe-8cd8-8fc333ab3759",
        "meta": {
          "profile": [
            "http://standardhealthrecord.org/fhir/StructureDefinition/shr-encounter-Encounter"
          ]
        },
        "status": "finished",
        "class": {
          "code": "ambulatory"
        },
        "type": [
          {
            "coding": [
              {
                "system": "http://snomed.info/sct",
                "code": "185345009"
              }
            ],
            "text": "Encounter for symptom"
          }
        ],
        "subject": {
          "reference": "urn:uuid:aa45a301-29d4-4ae6-a379-8efda70a0df4"
        },
        "period": {
          "start": "2013-03-26T17:50:07-04:00",
          "end": "2013-03-26T17:50:07-04:00"
        },
        "reason": {
          "coding": [
            {
              "system": "http://snomed.info/sct",
              "code": "10509002",
              "display": "Acute bronchitis (disorder)"
            }
          ]
        },
        "serviceProvider": {
          "reference": "urn:uuid:24180124-c1f3-45ef-9f02-7a0f74f9ff82"
        },
        "resourceType": "Encounter"
      }
    },
    {
      "fullUrl": "urn:uuid:eccadde3-e6fe-46a9-b22a-68f9b6e9615b",
      "resource": {
        "id": "eccadde3-e6fe-46a9-b22a-68f9b6e9615b",
        "meta": {
          "profile": [
            "http://standardhealthrecord.org/fhir/StructureDefinition/shr-problem-Problem"
          ]
        },
        "clinicalStatus": "active",
        "verificationStatus": "confirmed",
        "code": {
          "coding": [
            {
              "system": "http://snomed.info/sct",
              "code": "10509002",
              "display": "Acute bronchitis (disorder)"
            }
          ],
          "text": "Acute bronchitis (disorder)"
        },
        "subject": {
          "reference": "urn:uuid:aa45a301-29d4-4ae6-a379-8efda70a0df4"
        },
        "context": {
          "reference": "urn:uuid:2646424d-6b8d-4dfe-8cd8-8fc333ab3759"
        },
        "onsetDateTime": "2013-03-26T17:50:07-04:00",
        "abatementDateTime": "2013-04-12T15:58:58-04:00",
        "assertedDate": "2013-03-26",
        "resourceType": "Condition"
      }
    },
    {
      "resource": {
        "status": "completed",
        "category": [
          {
            "coding": [
              {
                "system": "http://snomed.info/sct",
                "code": "53950000",
                "display": "Respiratory therapy"
              }
            ]
          }
        ],
        "subject": {
          "reference": "urn:uuid:aa45a301-29d4-4ae6-a379-8efda70a0df4"
        },
        "context": {
          "reference": "urn:uuid:2646424d-6b8d-4dfe-8cd8-8fc333ab3759"
        },
        "period": {
          "start": "2013-03-26",
          "end": "2014-07-16"
        },
        "addresses": [
          {
            "reference": "urn:uuid:eccadde3-e6fe-46a9-b22a-68f9b6e9615b"
          }
        ],
        "activity": [
          {
            "detail": {
              "code": {
                "coding": [
                  {
                    "system": "http://snomed.info/sct",
                    "code": "304510005",
                    "display": "Recommendation to avoid exercise"
                  }
                ]
              },
              "status": "completed"
            }
          },
          {
            "detail": {
              "code": {
                "coding": [
                  {
                    "system": "http://snomed.info/sct",
                    "code": "371605008",
                    "display": "Deep breathing and coughing exercises"
                  }
                ]
              },
              "status": "completed"
            }
          }
        ],
        "resourceType": "CarePlan"
      }
    },
    {
      "resource": {
        "meta": {
          "profile": [
            "http://standardhealthrecord.org/fhir/StructureDefinition/shr-medication-Medication"
          ]
        },
        "code": {
          "coding": [
            {
              "system": "http://www.nlm.nih.gov/research/umls/rxnorm",
              "code": "1020137",
              "display": "Dextromethorphan Hydrobromide 1 MG/ML"
            }
          ],
          "text": "Dextromethorphan Hydrobromide 1 MG/ML"
        },
        "resourceType": "Medication"
      }
    },
    {
      "resource": {
        "meta": {
          "profile": [
            "http://standardhealthrecord.org/fhir/StructureDefinition/shr-medication-MedicationPrescription"
          ]
        },
        "extension": [
          {
            "url": "http://standardhealthrecord.org/fhir/StructureDefinition/shr-base-ActionCode-extension",
            "valueCodeableConcept": {
              "coding": [
                {
                  "system": "http://snomed.info/sct",
                  "code": "33633005",
                  "display": "Prescription of drug (procedure)"
                }
              ],
              "text": "Prescription of drug (procedure)"
            }
          }
        ],
        "status": "stopped",
        "medicationReference": {
          "reference": ""
        },
        "subject": {
          "reference": "urn:uuid:aa45a301-29d4-4ae6-a379-8efda70a0df4"
        },
        "context": {
          "reference": "urn:uuid:2646424d-6b8d-4dfe-8cd8-8fc333ab3759"
        },
        "authoredOn": "2013-03-26",
        "reasonReference": [
          {
            "reference": "urn:uuid:eccadde3-e6fe-46a9-b22a-68f9b6e9615b"
          }
        ],
        "dosageInstruction": [
          {

          }
        ],
        "resourceType": "MedicationRequest"
      }
    },
    {
      "fullUrl": "urn:uuid:f6ac8493-3c41-4418-9c4f-0332783440df",
      "resource": {
        "id": "f6ac8493-3c41-4418-9c4f-0332783440df",
        "meta": {
          "profile": [
            "http://standardhealthrecord.org/fhir/StructureDefinition/shr-encounter-Encounter"
          ]
        },
        "status": "finished",
        "class": {
          "code": "outpatient"
        },
        "type": [
          {
            "coding": [
              {
                "system": "http://snomed.info/sct",
                "code": "185349003"
              }
            ],
            "text": "Outpatient Encounter"
          }
        ],
        "subject": {
          "reference": "urn:uuid:aa45a301-29d4-4ae6-a379-8efda70a0df4"
        },
        "period": {
          "start": "2014-07-16T19:42:03-04:00",
          "end": "2014-07-16T20:42:03-04:00"
        },
        "serviceProvider": {
          "reference": "urn:uuid:24180124-c1f3-45ef-9f02-7a0f74f9ff82"
        },
        "resourceType": "Encounter"
      }
    },
    {
      "fullUrl": "urn:uuid:41ea1941-2d44-49af-883c-ad85a572728b",
      "resource": {
        "id": "41ea1941-2d44-49af-883c-ad85a572728b",
        "meta": {
          "profile": [
            "http://standardhealthrecord.org/fhir/StructureDefinition/shr-observation-Observation",
            "http://standardhealthrecord.org/fhir/StructureDefinition/shr-vital-VitalSign",
            "http://standardhealthrecord.org/fhir/StructureDefinition/shr-vital-BodyHeight"
          ]
        },
        "status": "final",
        "category": [
          {
            "coding": [
              {
                "system": "http://hl7.org/fhir/observation-category",
                "code": "vital-signs"
              }
            ]
          }
        ],
        "code": {
          "coding": [
            {
              "system": "http://loinc.org",
              "code": "8302-2",
              "display": "Body Height"
            }
          ],
          "text": "Body Height"
        },
        "subject": {
          "reference": "urn:uuid:aa45a301-29d4-4ae6-a379-8efda70a0df4"
        },
        "context": {
          "reference": "urn:uuid:f6ac8493-3c41-4418-9c4f-0332783440df"
        },
        "effectiveDateTime": "2014-07-16T19:42:03-04:00",
        "issued": "2014-07-16T19:42:03-04:00",
        "valueQuantity": {
          "value": 190.1848657986878,
          "unit": "cm",
          "system": "http://unitsofmeasure.org/",
          "code": "cm"
        },
        "resourceType": "Observation"
      }
    },
    {
      "fullUrl": "urn:uuid:20909509-7ce2-4b8a-8ff2-30545613213f",
      "resource": {
        "id": "20909509-7ce2-4b8a-8ff2-30545613213f",
        "meta": {
          "profile": [
            "http://standardhealthrecord.org/fhir/StructureDefinition/shr-observation-Observation",
            "http://standardhealthrecord.org/fhir/StructureDefinition/shr-vital-VitalSign",
            "http://standardhealthrecord.org/fhir/StructureDefinition/shr-vital-BodyWeight"
          ]
        },
        "status": "final",
        "category": [
          {
            "coding": [
              {
                "system": "http://hl7.org/fhir/observation-category",
                "code": "vital-signs"
              }
            ]
          }
        ],
        "code": {
          "coding": [
            {
              "system": "http://loinc.org",
              "code": "29463-7",
              "display": "Body Weight"
            }
          ],
          "text": "Body Weight"
        },
        "subject": {
          "reference": "urn:uuid:aa45a301-29d4-4ae6-a379-8efda70a0df4"
        },
        "context": {
          "reference": "urn:uuid:f6ac8493-3c41-4418-9c4f-0332783440df"
        },
        "effectiveDateTime": "2014-07-16T19:42:03-04:00",
        "issued": "2014-07-16T19:42:03-04:00",
        "valueQuantity": {
          "value": 93.34266972937684,
          "unit": "kg",
          "system": "http://unitsofmeasure.org/",
          "code": "kg"
        },
        "resourceType": "Observation"
      }
    },
    {
      "fullUrl": "urn:uuid:56b3a60a-215b-4ea8-a071-abd5b3ca783b",
      "resource": {
        "id": "56b3a60a-215b-4ea8-a071-abd5b3ca783b",
        "meta": {
          "profile": [
            "http://standardhealthrecord.org/fhir/StructureDefinition/shr-observation-Observation",
            "http://standardhealthrecord.org/fhir/StructureDefinition/shr-vital-VitalSign",
            "http://standardhealthrecord.org/fhir/StructureDefinition/shr-vital-BodyMassIndex"
          ]
        },
        "status": "final",
        "category": [
          {
            "coding": [
              {
                "system": "http://hl7.org/fhir/observation-category",
                "code": "vital-signs"
              }
            ]
          }
        ],
        "code": {
          "coding": [
            {
              "system": "http://loinc.org",
              "code": "39156-5",
              "display": "Body Mass Index"
            }
          ],
          "text": "Body Mass Index"
        },
        "subject": {
          "reference": "urn:uuid:aa45a301-29d4-4ae6-a379-8efda70a0df4"
        },
        "context": {
          "reference": "urn:uuid:f6ac8493-3c41-4418-9c4f-0332783440df"
        },
        "effectiveDateTime": "2014-07-16T19:42:03-04:00",
        "issued": "2014-07-16T19:42:03-04:00",
        "valueQuantity": {
          "value": 25.80645256985963,
          "unit": "kg/m2",
          "system": "http://unitsofmeasure.org/",
          "code": "kg/m2"
        },
        "resourceType": "Observation"
      }
    },
    {
      "fullUrl": "urn:uuid:06b2c860-9433-461d-b602-327444d9233e",
      "resource": {
        "id": "06b2c860-9433-461d-b602-327444d9233e",
        "meta": {
          "profile": [
            "http://standardhealthrecord.org/fhir/StructureDefinition/shr-observation-Observation",
            "http://standardhealthrecord.org/fhir/StructureDefinition/shr-vital-BloodPressure"
          ]
        },
        "status": "final",
        "category": [
          {
            "coding": [
              {
                "system": "http://hl7.org/fhir/observation-category",
                "code": "vital-signs"
              }
            ]
          }
        ],
        "code": {
          "coding": [
            {
              "system": "http://loinc.org",
              "code": "55284-4",
              "display": "Blood Pressure"
            }
          ]
        },
        "subject": {
          "reference": "urn:uuid:aa45a301-29d4-4ae6-a379-8efda70a0df4"
        },
        "context": {
          "reference": "urn:uuid:f6ac8493-3c41-4418-9c4f-0332783440df"
        },
        "effectiveDateTime": "2014-07-16T19:42:03-04:00",
        "issued": "2014-07-16T19:42:03-04:00",
        "component": [
          {
            "code": {
              "coding": [
                {
                  "system": "http://loinc.org",
                  "code": "8480-6",
                  "display": "Systolic Blood Pressure"
                }
              ],
              "text": "Systolic Blood Pressure"
            },
            "valueQuantity": {
              "value": 133,
              "unit": "mmHg",
              "system": "http://unitsofmeasure.org/",
              "code": "mmHg"
            }
          },
          {
            "code": {
              "coding": [
                {
                  "system": "http://loinc.org",
                  "code": "8462-4",
                  "display": "Diastolic Blood Pressure"
                }
              ],
              "text": "Diastolic Blood Pressure"
            },
            "valueQuantity": {
              "value": 72,
              "unit": "mmHg",
              "system": "http://unitsofmeasure.org/",
              "code": "mmHg"
            }
          }
        ],
        "resourceType": "Observation"
      }
    },
    {
      "fullUrl": "urn:uuid:c95b9bfe-9245-4a41-9d47-45143b8194da",
      "resource": {
        "id": "c95b9bfe-9245-4a41-9d47-45143b8194da",
        "meta": {
          "profile": [
            "http://standardhealthrecord.org/fhir/StructureDefinition/shr-observation-Observation"
          ]
        },
        "status": "final",
        "category": [
          {
            "coding": [
              {
                "system": "http://hl7.org/fhir/observation-category",
                "code": "laboratory"
              }
            ]
          }
        ],
        "code": {
          "coding": [
            {
              "system": "http://loinc.org",
              "code": "2093-3",
              "display": "Total Cholesterol"
            }
          ],
          "text": "Total Cholesterol"
        },
        "subject": {
          "reference": "urn:uuid:aa45a301-29d4-4ae6-a379-8efda70a0df4"
        },
        "context": {
          "reference": "urn:uuid:f6ac8493-3c41-4418-9c4f-0332783440df"
        },
        "effectiveDateTime": "2014-07-16T19:42:03-04:00",
        "issued": "2014-07-16T19:42:03-04:00",
        "valueQuantity": {
          "value": 191,
          "unit": "mg/dL",
          "system": "http://unitsofmeasure.org/",
          "code": "mg/dL"
        },
        "resourceType": "Observation"
      }
    },
    {
      "fullUrl": "urn:uuid:ec02c68f-6bb9-4278-bc1a-9152626658b1",
      "resource": {
        "id": "ec02c68f-6bb9-4278-bc1a-9152626658b1",
        "meta": {
          "profile": [
            "http://standardhealthrecord.org/fhir/StructureDefinition/shr-observation-Observation"
          ]
        },
        "status": "final",
        "category": [
          {
            "coding": [
              {
                "system": "http://hl7.org/fhir/observation-category",
                "code": "laboratory"
              }
            ]
          }
        ],
        "code": {
          "coding": [
            {
              "system": "http://loinc.org",
              "code": "2571-8",
              "display": "Triglycerides"
            }
          ],
          "text": "Triglycerides"
        },
        "subject": {
          "reference": "urn:uuid:aa45a301-29d4-4ae6-a379-8efda70a0df4"
        },
        "context": {
          "reference": "urn:uuid:f6ac8493-3c41-4418-9c4f-0332783440df"
        },
        "effectiveDateTime": "2014-07-16T19:42:03-04:00",
        "issued": "2014-07-16T19:42:03-04:00",
        "valueQuantity": {
          "value": 143,
          "unit": "mg/dL",
          "system": "http://unitsofmeasure.org/",
          "code": "mg/dL"
        },
        "resourceType": "Observation"
      }
    },
    {
      "fullUrl": "urn:uuid:d144cafc-3d95-4b88-a2de-5d0cf87aaf80",
      "resource": {
        "id": "d144cafc-3d95-4b88-a2de-5d0cf87aaf80",
        "meta": {
          "profile": [
            "http://standardhealthrecord.org/fhir/StructureDefinition/shr-observation-Observation"
          ]
        },
        "status": "final",
        "category": [
          {
            "coding": [
              {
                "system": "http://hl7.org/fhir/observation-category",
                "code": "laboratory"
              }
            ]
          }
        ],
        "code": {
          "coding": [
            {
              "system": "http://loinc.org",
              "code": "18262-6",
              "display": "Low Density Lipoprotein Cholesterol"
            }
          ],
          "text": "Low Density Lipoprotein Cholesterol"
        },
        "subject": {
          "reference": "urn:uuid:aa45a301-29d4-4ae6-a379-8efda70a0df4"
        },
        "context": {
          "reference": "urn:uuid:f6ac8493-3c41-4418-9c4f-0332783440df"
        },
        "effectiveDateTime": "2014-07-16T19:42:03-04:00",
        "issued": "2014-07-16T19:42:03-04:00",
        "valueQuantity": {
          "value": 90,
          "unit": "mg/dL",
          "system": "http://unitsofmeasure.org/",
          "code": "mg/dL"
        },
        "resourceType": "Observation"
      }
    },
    {
      "fullUrl": "urn:uuid:10a5bb96-a3a4-4b38-861f-0c4abb34335a",
      "resource": {
        "id": "10a5bb96-a3a4-4b38-861f-0c4abb34335a",
        "meta": {
          "profile": [
            "http://standardhealthrecord.org/fhir/StructureDefinition/shr-observation-Observation"
          ]
        },
        "status": "final",
        "category": [
          {
            "coding": [
              {
                "system": "http://hl7.org/fhir/observation-category",
                "code": "laboratory"
              }
            ]
          }
        ],
        "code": {
          "coding": [
            {
              "system": "http://loinc.org",
              "code": "2085-9",
              "display": "High Density Lipoprotein Cholesterol"
            }
          ],
          "text": "High Density Lipoprotein Cholesterol"
        },
        "subject": {
          "reference": "urn:uuid:aa45a301-29d4-4ae6-a379-8efda70a0df4"
        },
        "context": {
          "reference": "urn:uuid:f6ac8493-3c41-4418-9c4f-0332783440df"
        },
        "effectiveDateTime": "2014-07-16T19:42:03-04:00",
        "issued": "2014-07-16T19:42:03-04:00",
        "valueQuantity": {
          "value": 72,
          "unit": "mg/dL",
          "system": "http://unitsofmeasure.org/",
          "code": "mg/dL"
        },
        "resourceType": "Observation"
      }
    },
    {
      "fullUrl": "urn:uuid:b5f7b626-077e-4a16-add6-2ea2599310ed",
      "resource": {
        "id": "b5f7b626-077e-4a16-add6-2ea2599310ed",
        "meta": {
          "profile": [
            "http://standardhealthrecord.org/fhir/StructureDefinition/shr-observation-Panel"
          ]
        },
        "status": "final",
        "code": {
          "coding": [
            {
              "system": "http://loinc.org",
              "code": "57698-3",
              "display": "Lipid Panel"
            }
          ]
        },
        "subject": {
          "reference": "urn:uuid:aa45a301-29d4-4ae6-a379-8efda70a0df4"
        },
        "context": {
          "reference": "urn:uuid:f6ac8493-3c41-4418-9c4f-0332783440df"
        },
        "effectiveDateTime": "2014-07-16T19:42:03-04:00",
        "issued": "2014-07-16T19:42:03-04:00",
        "result": [
          {
            "reference": "urn:uuid:c95b9bfe-9245-4a41-9d47-45143b8194da",
            "display": "Total Cholesterol"
          },
          {
            "reference": "urn:uuid:ec02c68f-6bb9-4278-bc1a-9152626658b1",
            "display": "Triglycerides"
          },
          {
            "reference": "urn:uuid:d144cafc-3d95-4b88-a2de-5d0cf87aaf80",
            "display": "Low Density Lipoprotein Cholesterol"
          },
          {
            "reference": "urn:uuid:10a5bb96-a3a4-4b38-861f-0c4abb34335a",
            "display": "High Density Lipoprotein Cholesterol"
          }
        ],
        "resourceType": "DiagnosticReport"
      }
    },
    {
      "resource": {
        "meta": {
          "profile": [
            "http://standardhealthrecord.org/fhir/StructureDefinition/shr-immunization-Immunization"
          ]
        },
        "status": "completed",
        "notGiven": false,
        "vaccineCode": {
          "coding": [
            {
              "system": "http://hl7.org/fhir/sid/cvx",
              "code": "140",
              "display": "Influenza, seasonal, injectable, preservative free"
            }
          ],
          "text": "Influenza, seasonal, injectable, preservative free"
        },
        "patient": {
          "reference": "urn:uuid:aa45a301-29d4-4ae6-a379-8efda70a0df4"
        },
        "encounter": {
          "reference": "urn:uuid:f6ac8493-3c41-4418-9c4f-0332783440df"
        },
        "date": "2014-07-16T19:42:03-04:00",
        "primarySource": true,
        "resourceType": "Immunization"
      }
    }
  ],
  "resourceType": "Bundle"
}